pyproj/enums.py
pyproj/_transformer.pxd
pyproj/_transformer.pyi
pyproj/aoi.py
pyproj/_crs.pxd
pyproj/exceptions.py
pyproj/database.pyi
pyproj/network.py
pyproj/list.pyi
pyproj/database.pyx
pyproj/_network.pyx
pyproj/_compat.pxd
pyproj/geod.py
pyproj/_geod.cpython-39-x86_64-linux-gnu.so
pyproj/_transformer.pyx
pyproj/_crs.pyi
pyproj/database.cpython-39-x86_64-linux-gnu.so
pyproj/_sync.pyx
pyproj/_sync.pyi
pyproj/_crs.pyx
pyproj/_geod.pyx
pyproj/transformer.py
pyproj/_network.cpython-39-x86_64-linux-gnu.so
pyproj/_compat.pyi
pyproj/proj.py
pyproj/_compat.cpython-39-x86_64-linux-gnu.so
pyproj/utils.py
pyproj/base.pxi
pyproj/_compat.pyx
pyproj/proj.pxi
pyproj/datadir.py
pyproj/__main__.py
pyproj/_transformer.cpython-39-x86_64-linux-gnu.so
pyproj/_datadir.pyi
pyproj/_show_versions.py
pyproj/py.typed
pyproj/_datadir.cpython-39-x86_64-linux-gnu.so
pyproj/__init__.py
pyproj/sync.py
pyproj/_geod.pyi
pyproj/_crs.cpython-39-x86_64-linux-gnu.so
pyproj/_network.pyi
pyproj/list.cpython-39-x86_64-linux-gnu.so
pyproj/_sync.cpython-39-x86_64-linux-gnu.so
pyproj/list.pyx
pyproj/_geod.pxd
pyproj/_datadir.pyx
pyproj/_datadir.pxd
pyproj/proj_dir/share/proj/deformation_model.schema.json
pyproj/proj_dir/share/proj/triangulation.schema.json
pyproj/proj_dir/share/proj/proj.db
pyproj/proj_dir/share/proj/proj.ini
pyproj/proj_dir/share/proj/nad.lst
pyproj/proj_dir/share/proj/GL27
pyproj/proj_dir/share/proj/nad27
pyproj/proj_dir/share/proj/CH
pyproj/proj_dir/share/proj/nad83
pyproj/proj_dir/share/proj/world
pyproj/proj_dir/share/proj/ITRF2000
pyproj/proj_dir/share/proj/ITRF2014
pyproj/proj_dir/share/proj/other.extra
pyproj/proj_dir/share/proj/ITRF2008
pyproj/proj_dir/share/proj/projjson.schema.json
pyproj/crs/enums.py
pyproj/crs/crs.py
pyproj/crs/_cf1x8.py
pyproj/crs/coordinate_system.py
pyproj/crs/datum.py
pyproj/crs/__init__.py
pyproj/crs/coordinate_operation.py
pyproj.libs/libnghttp2-55af48d7.so.14.24.2
pyproj-3.6.0.dist-info/METADATA
pyproj-3.6.0.dist-info/LICENSE
pyproj-3.6.0.dist-info/top_level.txt
pyproj-3.6.0.dist-info/RECORD
pyproj-3.6.0.dist-info/entry_points.txt
pyproj-3.6.0.dist-info/LICENSE_proj
pyproj-3.6.0.dist-info/WHEEL
