Metadata-Version: 2.1
Name: pyproj
Version: 3.6.0
Summary: Python interface to PROJ (cartographic projections and coordinate transformations library)
Home-page: https://github.com/pyproj4/pyproj
Author-email: Jeff Whitaker <jeffrey.s.whitaker@noaa.gov>
Maintainer: pyproj contributors
License: MIT
Project-URL: homepage, https://pyproj4.github.io/pyproj/
Project-URL: documentation, https://pyproj4.github.io/pyproj/
Project-URL: repository, https://github.com/pyproj4/pyproj
Project-URL: changelog, https://pyproj4.github.io/pyproj/stable/history.html
Keywords: GIS,map,geospatial,coordinate-systems,coordinate-transformation,cartographic-projection,geodesic
Classifier: Development Status :: 4 - Beta
Classifier: Intended Audience :: Science/Research
Classifier: License :: OSI Approved :: MIT License
Classifier: Operating System :: OS Independent
Classifier: Programming Language :: Python
Classifier: Programming Language :: Python :: 3.9
Classifier: Programming Language :: Python :: 3.10
Classifier: Programming Language :: Python :: 3.11
Classifier: Programming Language :: Python :: 3 :: Only
Classifier: Topic :: Scientific/Engineering
Classifier: Topic :: Scientific/Engineering :: GIS
Classifier: Topic :: Scientific/Engineering :: Mathematics
Classifier: Topic :: Software Development :: Libraries :: Python Modules
Classifier: Typing :: Typed
Requires-Python: >=3.9
License-File: LICENSE
License-File: LICENSE_proj
